fmlcli.py
fmlcli-1.0.16.dist-info/entry_points.txt
fmlcli-1.0.16.dist-info/METADATA
fmlcli-1.0.16.dist-info/WHEEL
fmlcli-1.0.16.dist-info/RECORD
