Metadata-Version: 2.1
Name: fmlcli
Version: 1.0.16
Summary: 
Author: Alexstrasza03
Author-email: 77481463+Alexstrasza03@users.noreply.github.com
Requires-Python: >=3.8,<4.0
Classifier: Programming Language :: Python :: 3
Classifier: Programming Language :: Python :: 3.8
Classifier: Programming Language :: Python :: 3.9
Classifier: Programming Language :: Python :: 3.10
Classifier: Programming Language :: Python :: 3.11
Classifier: Programming Language :: Python :: 3.12
Requires-Dist: argparse (==1.4.0)
Requires-Dist: glitter-sdk (==1.0.3)
Requires-Dist: rich (==13.7.1)
